mtrip-0.3.0.dist-info/RECORD
mtrip-0.3.0.dist-info/LICENSE
mtrip-0.3.0.dist-info/WHEEL
mtrip-0.3.0.dist-info/entry_points.txt
mtrip-0.3.0.dist-info/top_level.txt
mtrip-0.3.0.dist-info/METADATA
mtrip/scipy_comb.pyx
mtrip/scipycomb.cpython-311-darwin.so
mtrip/bitsnbobs.cpython-311-darwin.so
mtrip/__init__.py
mtrip/bitsnbobs.c
mtrip/snoob.py
mtrip/median_tree_reconstruction.py
mtrip/scipy_comb.c
mtrip/triplet_omp_py.pyx
mtrip/triplet_omp.cpython-311-darwin.so
mtrip/py.typed
mtrip/triplet_omp_py.c
mtrip/bitsnbobs.pyx
mtrip/cli/mtrip_combine_cmd.py
mtrip/cli/mtrip_suboptimal_cmd.py
mtrip/cli/__init__.py
mtrip/cli/mtrip_cmd.py
mtrip/_c_ext/weights_omp.h
mtrip/_c_ext/CMakeLists.txt
mtrip/_c_ext/lookup_table.c
mtrip/_c_ext/weights_omp.c
mtrip/_c_ext/lookup_table.h
mtrip/.dylibs/libomp.dylib
