Metadata-Version: 2.2
Name: mtrip
Version: 0.3.0
Summary: A package for finding the exact median triplet tree (in the context of phylogenetics)
Author-email: Gleb Zhelezov <gleb@glebzh.com>
License: GPLv3
Project-URL: Homepage, https://github.com/glebzhelezov/rtist
Project-URL: Issues, https://github.com/glebzhelezov/rtist/issues
Classifier: Programming Language :: Python :: 3
Classifier: License :: OSI Approved :: GNU General Public License v3 (GPLv3)
Classifier: Operating System :: OS Independent
Requires-Python: >=3.10
License-File: LICENSE
Requires-Dist: Cython>=3.0.0
Requires-Dist: cysignals
Provides-Extra: dev
Requires-Dist: pytest>=6.0; extra == "dev"
Requires-Dist: black; extra == "dev"
Requires-Dist: mypy; extra == "dev"
